MANIFEST.in
README.rst
setup.cfg
setup.py
test.sh
src/ctotable.c
totable/__init__.py
totable.egg-info/PKG-INFO
totable.egg-info/SOURCES.txt
totable.egg-info/dependency_links.txt
totable.egg-info/top_level.txt
totable/tests/test_totable.py