Metadata-Version: 1.0
Name: totable
Version: 0.1
Summary: Cython wrapper for tokyo cabinet table
Home-page: http://
Author: brentp
Author-email: bpederse@gmail.com
License: UNKNOWN
Download-URL: http://
Platform: UNKNOWN
Classifier: Development Status :: 3 - Alpha
Classifier: Intended Audience :: Developers
Classifier: License :: OSI Approved :: BSD License
Classifier: Operating System :: OS Independent
Classifier: Programming Language :: Python
Classifier: Programming Language :: C
Classifier: Topic :: Database :: Database Engines/Servers
